oscrypto_tests/__init__.py
oscrypto_tests/__main__.py
oscrypto_tests/_https_client.py
oscrypto_tests/_socket_proxy.py
oscrypto_tests/_socket_server.py
oscrypto_tests/_unittest_compat.py
oscrypto_tests/exception_context.py
oscrypto_tests/test_asymmetric.py
oscrypto_tests/test_init.py
oscrypto_tests/test_kdf.py
oscrypto_tests/test_keys.py
oscrypto_tests/test_symmetric.py
oscrypto_tests/test_tls.py
oscrypto_tests/test_trust_list.py
oscrypto_tests/unittest_data.py
oscrypto_tests/fixtures/.DS_Store
oscrypto_tests/fixtures/DSAParametersInheritedCACert.crt
oscrypto_tests/fixtures/badtls.io_ca.crt
oscrypto_tests/fixtures/digicert_ca.crt
oscrypto_tests/fixtures/dsa_signature
oscrypto_tests/fixtures/ecdsa_signature
oscrypto_tests/fixtures/message.sha1
oscrypto_tests/fixtures/message.sha256
oscrypto_tests/fixtures/message.txt
oscrypto_tests/fixtures/rsa_pss_signature
oscrypto_tests/fixtures/rsa_pss_signature_pss_cert
oscrypto_tests/fixtures/rsa_public_encrypted
oscrypto_tests/fixtures/rsa_public_encrypted_oaep
oscrypto_tests/fixtures/rsa_signature
oscrypto_tests/fixtures/rsa_signature_raw
oscrypto_tests/fixtures/keys/test-4096.crt
oscrypto_tests/fixtures/keys/test-4096.key
oscrypto_tests/fixtures/keys/test-aes128.key
oscrypto_tests/fixtures/keys/test-aes128.p12
oscrypto_tests/fixtures/keys/test-aes256.key
oscrypto_tests/fixtures/keys/test-aes256.p12
oscrypto_tests/fixtures/keys/test-der.crt
oscrypto_tests/fixtures/keys/test-der.key
oscrypto_tests/fixtures/keys/test-dsa-1024-der.crt
oscrypto_tests/fixtures/keys/test-dsa-1024-der.key
oscrypto_tests/fixtures/keys/test-dsa-1024.crt
oscrypto_tests/fixtures/keys/test-dsa-1024.key
oscrypto_tests/fixtures/keys/test-dsa-1024.param
oscrypto_tests/fixtures/keys/test-dsa-2048-der.crt
oscrypto_tests/fixtures/keys/test-dsa-2048-der.key
oscrypto_tests/fixtures/keys/test-dsa-2048-sha2-der.crt
oscrypto_tests/fixtures/keys/test-dsa-2048-sha2-der.key
oscrypto_tests/fixtures/keys/test-dsa-2048-sha2.crt
oscrypto_tests-1.3.0.dist-info/LICENSE
oscrypto_tests-1.3.0.dist-info/METADATA
oscrypto_tests-1.3.0.dist-info/WHEEL
oscrypto_tests-1.3.0.dist-info/top_level.txt
oscrypto_tests-1.3.0.dist-info/RECORD
